OBP_logging_v3/__init__.py
OBP_logging_v3/cloudwatch.py
OBP_logging_v3/rds.py
OBP_logging_v3/utils.py
OBP_logging_v3-0.0.1.dist-info/METADATA
OBP_logging_v3-0.0.1.dist-info/WHEEL
OBP_logging_v3-0.0.1.dist-info/top_level.txt
OBP_logging_v3-0.0.1.dist-info/RECORD
